compoundercalc/__init__.py
compoundercalc/compounder.py
compoundercalc/cosa.py
compoundercalc-0.1.0.dist-info/METADATA
compoundercalc-0.1.0.dist-info/WHEEL
compoundercalc-0.1.0.dist-info/top_level.txt
compoundercalc-0.1.0.dist-info/RECORD
