Metadata-Version: 2.1
Name: compoundercalc
Version: 0.1.0
Summary: A package for compound interest calculations
Home-page: https://github.com/croketillo/compoundercalc
Author: Croketillo
Author-email: croketillo@gmail.com
License: GNU v3
Classifier: Development Status :: 3 - Alpha
Classifier: Intended Audience :: Financial and Insurance Industry
Classifier: License :: OSI Approved :: GNU General Public License v3 (GPLv3)
Classifier: Programming Language :: Python :: 3
Classifier: Programming Language :: Python :: 3.7
Classifier: Programming Language :: Python :: 3.8
Classifier: Programming Language :: Python :: 3.9
Classifier: Programming Language :: Python :: 3.10
Requires-Python: >=3.7
